piglatin/__init__.py
piglatin-1.0.6.dist-info/LICENSE
piglatin-1.0.6.dist-info/WHEEL
piglatin-1.0.6.dist-info/METADATA
piglatin-1.0.6.dist-info/RECORD
