Metadata-Version: 2.1
Name: piglatin
Version: 1.0.6
Summary: Converts text to Pig Latin
Home-page: https://github.com/bpabel/piglatin
License: UNKNOWN
Keywords: piglatin,translate,cypher,secret,language
Author: Brendan Abel
Author-email: 007brendan@gmail.com
Requires-Python: >=2.7
Classifier: License :: OSI Approved :: MIT License
Classifier: Topic :: Text Processing
Classifier: Topic :: Text Processing :: General
Classifier: Topic :: Text Processing :: Linguistic
